[
    {
        "trends": [
            {
                "name": "#VidasNegrasImportam",
                "url": "http://twitter.com/search?q=%23VidasNegrasImportam",
                "promoted_content": null,
                "query": "%23VidasNegrasImportam",
                "tweet_volume": 571734
            },
            {
                "name": "#ForaBol\u5350onaro",
                "url": "http://twitter.com/search?q=%23ForaBol%E5%8D%90onaro",
                "promoted_content": null,
                "query": "%23ForaBol%E5%8D%90onaro",
                "tweet_volume": 126063
            },
            {
                "name": "#AntifaTERRORISTA",
                "url": "http://twitter.com/search?q=%23AntifaTERRORISTA",
                "promoted_content": null,
                "query": "%23AntifaTERRORISTA",
                "tweet_volume": 127063
            },
            {
                "name": "Ucr\u00e2nia",
                "url": "http://twitter.com/search?q=Ucr%C3%A2nia",
                "promoted_content": null,
                "query": "Ucr%C3%A2nia",
                "tweet_volume": 54676
            },
            {
                "name": "Paulista",
                "url": "http://twitter.com/search?q=Paulista",
                "promoted_content": null,
                "query": "Paulista",
                "tweet_volume": 376225
            },
            {
                "name": "#CNNLixo",
                "url": "http://twitter.com/search?q=%23CNNLixo",
                "promoted_content": null,
                "query": "%23CNNLixo",
                "tweet_volume": 48394
            },
            {
                "name": "SporTV",
                "url": "http://twitter.com/search?q=SporTV",
                "promoted_content": null,
                "query": "SporTV",
                "tweet_volume": null
            },
            {
                "name": "David Luiz",
                "url": "http://twitter.com/search?q=%22David+Luiz%22",
                "promoted_content": null,
                "query": "%22David+Luiz%22",
                "tweet_volume": null
            },
            {
                "name": "#POPLineMasks4All",
                "url": "http://twitter.com/search?q=%23POPLineMasks4All",
                "promoted_content": null,
                "query": "%23POPLineMasks4All",
                "tweet_volume": 12892
            },
            {
                "name": "kristen bell",
                "url": "http://twitter.com/search?q=%22kristen+bell%22",
                "promoted_content": null,
                "query": "%22kristen+bell%22",
                "tweet_volume": null
            },
            {
                "name": "Geraldo Azevedo",
                "url": "http://twitter.com/search?q=%22Geraldo+Azevedo%22",
                "promoted_content": null,
                "query": "%22Geraldo+Azevedo%22",
                "tweet_volume": null
            },
            {
                "name": "Seu Jorge",
                "url": "http://twitter.com/search?q=%22Seu+Jorge%22",
                "promoted_content": null,
                "query": "%22Seu+Jorge%22",
                "tweet_volume": null
            },
            {
                "name": "O Fred",
                "url": "http://twitter.com/search?q=%22O+Fred%22",
                "promoted_content": null,
                "query": "%22O+Fred%22",
                "tweet_volume": 49021
            },
            {
                "name": "Bernard",
                "url": "http://twitter.com/search?q=Bernard",
                "promoted_content": null,
                "query": "Bernard",
                "tweet_volume": 11509
            },
            {
                "name": "Alexandre Pires",
                "url": "http://twitter.com/search?q=%22Alexandre+Pires%22",
                "promoted_content": null,
                "query": "%22Alexandre+Pires%22",
                "tweet_volume": null
            },
            {
                "name": "Gavi\u00f5es",
                "url": "http://twitter.com/search?q=Gavi%C3%B5es",
                "promoted_content": null,
                "query": "Gavi%C3%B5es",
                "tweet_volume": 172234
            },
            {
                "name": "Evair",
                "url": "http://twitter.com/search?q=Evair",
                "promoted_content": null,
                "query": "Evair",
                "tweet_volume": null
            },
            {
                "name": "Veterano",
                "url": "http://twitter.com/search?q=Veterano",
                "promoted_content": null,
                "query": "Veterano",
                "tweet_volume": null
            },
            {
                "name": "Khedira",
                "url": "http://twitter.com/search?q=Khedira",
                "promoted_content": null,
                "query": "Khedira",
                "tweet_volume": null
            },
            {
                "name": "M\u00e1rio S\u00e9rgio",
                "url": "http://twitter.com/search?q=%22M%C3%A1rio+S%C3%A9rgio%22",
                "promoted_content": null,
                "query": "%22M%C3%A1rio+S%C3%A9rgio%22",
                "tweet_volume": null
            },
            {
                "name": "Fascismo",
                "url": "http://twitter.com/search?q=Fascismo",
                "promoted_content": null,
                "query": "Fascismo",
                "tweet_volume": 240800
            },
            {
                "name": "Cavalieri",
                "url": "http://twitter.com/search?q=Cavalieri",
                "promoted_content": null,
                "query": "Cavalieri",
                "tweet_volume": null
            },
            {
                "name": "\u00e9 campe\u00e3o",
                "url": "http://twitter.com/search?q=%22%C3%A9+campe%C3%A3o%22",
                "promoted_content": null,
                "query": "%22%C3%A9+campe%C3%A3o%22",
                "tweet_volume": null
            },
            {
                "name": "Cazares",
                "url": "http://twitter.com/search?q=Cazares",
                "promoted_content": null,
                "query": "Cazares",
                "tweet_volume": null
            },
            {
                "name": "DIGUINHO",
                "url": "http://twitter.com/search?q=DIGUINHO",
                "promoted_content": null,
                "query": "DIGUINHO",
                "tweet_volume": null
            },
            {
                "name": "tinashe",
                "url": "http://twitter.com/search?q=tinashe",
                "promoted_content": null,
                "query": "tinashe",
                "tweet_volume": 175943
            },
            {
                "name": "C\u00edrio",
                "url": "http://twitter.com/search?q=C%C3%ADrio",
                "promoted_content": null,
                "query": "C%C3%ADrio",
                "tweet_volume": null
            },
            {
                "name": "Datolo",
                "url": "http://twitter.com/search?q=Datolo",
                "promoted_content": null,
                "query": "Datolo",
                "tweet_volume": null
            },
            {
                "name": "Facista",
                "url": "http://twitter.com/search?q=Facista",
                "promoted_content": null,
                "query": "Facista",
                "tweet_volume": 22821
            },
            {
                "name": "Churchill",
                "url": "http://twitter.com/search?q=Churchill",
                "promoted_content": null,
                "query": "Churchill",
                "tweet_volume": 20413
            },
            {
                "name": "Gid\u00e3o",
                "url": "http://twitter.com/search?q=Gid%C3%A3o",
                "promoted_content": null,
                "query": "Gid%C3%A3o",
                "tweet_volume": null
            },
            {
                "name": "#Fant\u00e1stico",
                "url": "http://twitter.com/search?q=%23Fant%C3%A1stico",
                "promoted_content": null,
                "query": "%23Fant%C3%A1stico",
                "tweet_volume": null
            },
            {
                "name": "#FascistasNaoPassarao",
                "url": "http://twitter.com/search?q=%23FascistasNaoPassarao",
                "promoted_content": null,
                "query": "%23FascistasNaoPassarao",
                "tweet_volume": 14850
            },
            {
                "name": "#NadaPraFazerEmCasa",
                "url": "http://twitter.com/search?q=%23NadaPraFazerEmCasa",
                "promoted_content": null,
                "query": "%23NadaPraFazerEmCasa",
                "tweet_volume": null
            },
            {
                "name": "#SkolNaLivedaSol",
                "url": "http://twitter.com/search?q=%23SkolNaLivedaSol",
                "promoted_content": null,
                "query": "%23SkolNaLivedaSol",
                "tweet_volume": null
            },
            {
                "name": "#ChurrasdaYas",
                "url": "http://twitter.com/search?q=%23ChurrasdaYas",
                "promoted_content": null,
                "query": "%23ChurrasdaYas",
                "tweet_volume": null
            },
            {
                "name": "#Somos57MLHOES",
                "url": "http://twitter.com/search?q=%23Somos57MLHOES",
                "promoted_content": null,
                "query": "%23Somos57MLHOES",
                "tweet_volume": null
            },
            {
                "name": "#SalveOMatoDoJulio",
                "url": "http://twitter.com/search?q=%23SalveOMatoDoJulio",
                "promoted_content": null,
                "query": "%23SalveOMatoDoJulio",
                "tweet_volume": null
            },
            {
                "name": "#faixaespecial",
                "url": "http://twitter.com/search?q=%23faixaespecial",
                "promoted_content": null,
                "query": "%23faixaespecial",
                "tweet_volume": null
            },
            {
                "name": "#exposedaracaju",
                "url": "http://twitter.com/search?q=%23exposedaracaju",
                "promoted_content": null,
                "query": "%23exposedaracaju",
                "tweet_volume": null
            },
            {
                "name": "#VaiTePegar",
                "url": "http://twitter.com/search?q=%23VaiTePegar",
                "promoted_content": null,
                "query": "%23VaiTePegar",
                "tweet_volume": 31275
            },
            {
                "name": "#PolloTaEmCasaLive",
                "url": "http://twitter.com/search?q=%23PolloTaEmCasaLive",
                "promoted_content": null,
                "query": "%23PolloTaEmCasaLive",
                "tweet_volume": null
            },
            {
                "name": "#bolaobabycat",
                "url": "http://twitter.com/search?q=%23bolaobabycat",
                "promoted_content": null,
                "query": "%23bolaobabycat",
                "tweet_volume": null
            },
            {
                "name": "#LiveEvaOrigem",
                "url": "http://twitter.com/search?q=%23LiveEvaOrigem",
                "promoted_content": null,
                "query": "%23LiveEvaOrigem",
                "tweet_volume": null
            },
            {
                "name": "#COPAFF",
                "url": "http://twitter.com/search?q=%23COPAFF",
                "promoted_content": null,
                "query": "%23COPAFF",
                "tweet_volume": null
            },
            {
                "name": "#anonymus",
                "url": "http://twitter.com/search?q=%23anonymus",
                "promoted_content": null,
                "query": "%23anonymus",
                "tweet_volume": 91309
            },
            {
                "name": "#livevouprosereno",
                "url": "http://twitter.com/search?q=%23livevouprosereno",
                "promoted_content": null,
                "query": "%23livevouprosereno",
                "tweet_volume": null
            },
            {
                "name": "#FluTetr4",
                "url": "http://twitter.com/search?q=%23FluTetr4",
                "promoted_content": null,
                "query": "%23FluTetr4",
                "tweet_volume": 21768
            },
            {
                "name": "#DomingoEspetacular",
                "url": "http://twitter.com/search?q=%23DomingoEspetacular",
                "promoted_content": null,
                "query": "%23DomingoEspetacular",
                "tweet_volume": null
            },
            {
                "name": "#Eliana",
                "url": "http://twitter.com/search?q=%23Eliana",
                "promoted_content": null,
                "query": "%23Eliana",
                "tweet_volume": null
            }
        ],
        "as_of": "2020-05-31T23:23:52Z",
        "created_at": "2020-05-31T23:18:55Z",
        "locations": [
            {
                "name": "Brazil",
                "woeid": 23424768
            }
        ]
    }
]