[
    {
        "trends": [
            {
                "name": "Top 4",
                "url": "http://twitter.com/search?q=%22Top+4%22",
                "promoted_content": null,
                "query": "%22Top+4%22",
                "tweet_volume": 29520
            },
            {
                "name": "#cidadealertarj",
                "url": "http://twitter.com/search?q=%23cidadealertarj",
                "promoted_content": null,
                "query": "%23cidadealertarj",
                "tweet_volume": null
            },
            {
                "name": "#melimnobbb",
                "url": "http://twitter.com/search?q=%23melimnobbb",
                "promoted_content": null,
                "query": "%23melimnobbb",
                "tweet_volume": null
            },
            {
                "name": "#futebolnaveia",
                "url": "http://twitter.com/search?q=%23futebolnaveia",
                "promoted_content": null,
                "query": "%23futebolnaveia",
                "tweet_volume": null
            },
            {
                "name": "#chuvarj",
                "url": "http://twitter.com/search?q=%23chuvarj",
                "promoted_content": null,
                "query": "%23chuvarj",
                "tweet_volume": null
            },
            {
                "name": "#OurMusicianRos\u00e9Day",
                "url": "http://twitter.com/search?q=%23OurMusicianRos%C3%A9Day",
                "promoted_content": null,
                "query": "%23OurMusicianRos%C3%A9Day",
                "tweet_volume": 1029605
            },
            {
                "name": "O Fred",
                "url": "http://twitter.com/search?q=%22O+Fred%22",
                "promoted_content": null,
                "query": "%22O+Fred%22",
                "tweet_volume": null
            },
            {
                "name": "The Witcher 3",
                "url": "http://twitter.com/search?q=%22The+Witcher+3%22",
                "promoted_content": null,
                "query": "%22The+Witcher+3%22",
                "tweet_volume": null
            },
            {
                "name": "Patr\u00edcia L\u00e9lis",
                "url": "http://twitter.com/search?q=%22Patr%C3%ADcia+L%C3%A9lis%22",
                "promoted_content": null,
                "query": "%22Patr%C3%ADcia+L%C3%A9lis%22",
                "tweet_volume": 14847
            },
            {
                "name": "Se a Bianca",
                "url": "http://twitter.com/search?q=%22Se+a+Bianca%22",
                "promoted_content": null,
                "query": "%22Se+a+Bianca%22",
                "tweet_volume": 66994
            },
            {
                "name": "gizelly e thelma",
                "url": "http://twitter.com/search?q=%22gizelly+e+thelma%22",
                "promoted_content": null,
                "query": "%22gizelly+e+thelma%22",
                "tweet_volume": 11710
            },
            {
                "name": "Super Mario World",
                "url": "http://twitter.com/search?q=%22Super+Mario+World%22",
                "promoted_content": null,
                "query": "%22Super+Mario+World%22",
                "tweet_volume": null
            },
            {
                "name": "Xereca",
                "url": "http://twitter.com/search?q=Xereca",
                "promoted_content": null,
                "query": "Xereca",
                "tweet_volume": 24994
            },
            {
                "name": "QUEREMOS MAIS GABICENTE",
                "url": "http://twitter.com/search?q=%22QUEREMOS+MAIS+GABICENTE%22",
                "promoted_content": null,
                "query": "%22QUEREMOS+MAIS+GABICENTE%22",
                "tweet_volume": null
            },
            {
                "name": "Yaravirus",
                "url": "http://twitter.com/search?q=Yaravirus",
                "promoted_content": null,
                "query": "Yaravirus",
                "tweet_volume": null
            },
            {
                "name": "TWITTER VERIFICA EULUCASVIANA",
                "url": "http://twitter.com/search?q=%22TWITTER+VERIFICA+EULUCASVIANA%22",
                "promoted_content": null,
                "query": "%22TWITTER+VERIFICA+EULUCASVIANA%22",
                "tweet_volume": null
            },
            {
                "name": "Lagoa da Pampulha",
                "url": "http://twitter.com/search?q=%22Lagoa+da+Pampulha%22",
                "promoted_content": null,
                "query": "%22Lagoa+da+Pampulha%22",
                "tweet_volume": null
            },
            {
                "name": "World of Warcraft",
                "url": "http://twitter.com/search?q=%22World+of+Warcraft%22",
                "promoted_content": null,
                "query": "%22World+of+Warcraft%22",
                "tweet_volume": null
            },
            {
                "name": "Qinni",
                "url": "http://twitter.com/search?q=Qinni",
                "promoted_content": null,
                "query": "Qinni",
                "tweet_volume": 126263
            },
            {
                "name": "PORTUGUESE SUBTITTLE",
                "url": "http://twitter.com/search?q=%22PORTUGUESE+SUBTITTLE%22",
                "promoted_content": null,
                "query": "%22PORTUGUESE+SUBTITTLE%22",
                "tweet_volume": null
            },
            {
                "name": "Eduardo Baptista",
                "url": "http://twitter.com/search?q=%22Eduardo+Baptista%22",
                "promoted_content": null,
                "query": "%22Eduardo+Baptista%22",
                "tweet_volume": null
            },
            {
                "name": "\u00c0 Procura da Felicidade",
                "url": "http://twitter.com/search?q=%22%C3%80+Procura+da+Felicidade%22",
                "promoted_content": null,
                "query": "%22%C3%80+Procura+da+Felicidade%22",
                "tweet_volume": null
            },
            {
                "name": "daniel mu\u00f1oz",
                "url": "http://twitter.com/search?q=%22daniel+mu%C3%B1oz%22",
                "promoted_content": null,
                "query": "%22daniel+mu%C3%B1oz%22",
                "tweet_volume": null
            },
            {
                "name": "Counter Strike",
                "url": "http://twitter.com/search?q=%22Counter+Strike%22",
                "promoted_content": null,
                "query": "%22Counter+Strike%22",
                "tweet_volume": null
            },
            {
                "name": "Cruzeiro x S\u00e3o Paulo",
                "url": "http://twitter.com/search?q=%22Cruzeiro+x+S%C3%A3o+Paulo%22",
                "promoted_content": null,
                "query": "%22Cruzeiro+x+S%C3%A3o+Paulo%22",
                "tweet_volume": null
            },
            {
                "name": "Guitar Hero",
                "url": "http://twitter.com/search?q=%22Guitar+Hero%22",
                "promoted_content": null,
                "query": "%22Guitar+Hero%22",
                "tweet_volume": null
            },
            {
                "name": "Lamborghini",
                "url": "http://twitter.com/search?q=Lamborghini",
                "promoted_content": null,
                "query": "Lamborghini",
                "tweet_volume": null
            },
            {
                "name": "Arlington",
                "url": "http://twitter.com/search?q=Arlington",
                "promoted_content": null,
                "query": "Arlington",
                "tweet_volume": null
            },
            {
                "name": "Armando",
                "url": "http://twitter.com/search?q=Armando",
                "promoted_content": null,
                "query": "Armando",
                "tweet_volume": 36177
            },
            {
                "name": "Club Penguin",
                "url": "http://twitter.com/search?q=%22Club+Penguin%22",
                "promoted_content": null,
                "query": "%22Club+Penguin%22",
                "tweet_volume": null
            },
            {
                "name": "Chrono Trigger",
                "url": "http://twitter.com/search?q=%22Chrono+Trigger%22",
                "promoted_content": null,
                "query": "%22Chrono+Trigger%22",
                "tweet_volume": null
            },
            {
                "name": "Red Dead Redemption 2",
                "url": "http://twitter.com/search?q=%22Red+Dead+Redemption+2%22",
                "promoted_content": null,
                "query": "%22Red+Dead+Redemption+2%22",
                "tweet_volume": null
            },
            {
                "name": "#oioioi91",
                "url": "http://twitter.com/search?q=%23oioioi91",
                "promoted_content": null,
                "query": "%23oioioi91",
                "tweet_volume": null
            },
            {
                "name": "#QueenRadio",
                "url": "http://twitter.com/search?q=%23QueenRadio",
                "promoted_content": null,
                "query": "%23QueenRadio",
                "tweet_volume": 127790
            },
            {
                "name": "#mtvtop20ver\u00e3o",
                "url": "http://twitter.com/search?q=%23mtvtop20ver%C3%A3o",
                "promoted_content": null,
                "query": "%23mtvtop20ver%C3%A3o",
                "tweet_volume": null
            },
            {
                "name": "#\uace8\ub4e0\ubcf4\uc774\uc2a4_\ub85c\uc81c\ub370\uc774",
                "url": "http://twitter.com/search?q=%23%EA%B3%A8%EB%93%A0%EB%B3%B4%EC%9D%B4%EC%8A%A4_%EB%A1%9C%EC%A0%9C%EB%8D%B0%EC%9D%B4",
                "promoted_content": null,
                "query": "%23%EA%B3%A8%EB%93%A0%EB%B3%B4%EC%9D%B4%EC%8A%A4_%EB%A1%9C%EC%A0%9C%EB%8D%B0%EC%9D%B4",
                "tweet_volume": 856006
            },
            {
                "name": "#ComebackShonda",
                "url": "http://twitter.com/search?q=%23ComebackShonda",
                "promoted_content": null,
                "query": "%23ComebackShonda",
                "tweet_volume": null
            },
            {
                "name": "#mtvhitsfresquinho",
                "url": "http://twitter.com/search?q=%23mtvhitsfresquinho",
                "promoted_content": null,
                "query": "%23mtvhitsfresquinho",
                "tweet_volume": null
            },
            {
                "name": "#NhonhoPauteAMP895",
                "url": "http://twitter.com/search?q=%23NhonhoPauteAMP895",
                "promoted_content": null,
                "query": "%23NhonhoPauteAMP895",
                "tweet_volume": 10938
            },
            {
                "name": "#PT40anosDeLutas",
                "url": "http://twitter.com/search?q=%23PT40anosDeLutas",
                "promoted_content": null,
                "query": "%23PT40anosDeLutas",
                "tweet_volume": null
            },
            {
                "name": "#graffite98",
                "url": "http://twitter.com/search?q=%23graffite98",
                "promoted_content": null,
                "query": "%23graffite98",
                "tweet_volume": null
            },
            {
                "name": "#FofocalizandoNoSBT",
                "url": "http://twitter.com/search?q=%23FofocalizandoNoSBT",
                "promoted_content": null,
                "query": "%23FofocalizandoNoSBT",
                "tweet_volume": null
            },
            {
                "name": "#EleitoresdoEmbaixador",
                "url": "http://twitter.com/search?q=%23EleitoresdoEmbaixador",
                "promoted_content": null,
                "query": "%23EleitoresdoEmbaixador",
                "tweet_volume": null
            },
            {
                "name": "#BettyAFeiaEmNY011",
                "url": "http://twitter.com/search?q=%23BettyAFeiaEmNY011",
                "promoted_content": null,
                "query": "%23BettyAFeiaEmNY011",
                "tweet_volume": null
            },
            {
                "name": "#AskOriana",
                "url": "http://twitter.com/search?q=%23AskOriana",
                "promoted_content": null,
                "query": "%23AskOriana",
                "tweet_volume": null
            },
            {
                "name": "#BrasilUrgente",
                "url": "http://twitter.com/search?q=%23BrasilUrgente",
                "promoted_content": null,
                "query": "%23BrasilUrgente",
                "tweet_volume": null
            },
            {
                "name": "#AbismoDePaixao120",
                "url": "http://twitter.com/search?q=%23AbismoDePaixao120",
                "promoted_content": null,
                "query": "%23AbismoDePaixao120",
                "tweet_volume": null
            },
            {
                "name": "#FernandoESorocabaNoTVZ",
                "url": "http://twitter.com/search?q=%23FernandoESorocabaNoTVZ",
                "promoted_content": null,
                "query": "%23FernandoESorocabaNoTVZ",
                "tweet_volume": null
            },
            {
                "name": "#proenemaovivo",
                "url": "http://twitter.com/search?q=%23proenemaovivo",
                "promoted_content": null,
                "query": "%23proenemaovivo",
                "tweet_volume": null
            },
            {
                "name": "#fsradiobrasil",
                "url": "http://twitter.com/search?q=%23fsradiobrasil",
                "promoted_content": null,
                "query": "%23fsradiobrasil",
                "tweet_volume": null
            }
        ],
        "as_of": "2020-02-10T22:21:52Z",
        "created_at": "2020-02-10T22:18:25Z",
        "locations": [
            {
                "name": "Brazil",
                "woeid": 23424768
            }
        ]
    }
]