[
    {
        "trends": [
            {
                "name": "#AvenidaBrasil",
                "url": "http://twitter.com/search?q=%23AvenidaBrasil",
                "promoted_content": null,
                "query": "%23AvenidaBrasil",
                "tweet_volume": 133983
            },
            {
                "name": "Mandetta",
                "url": "http://twitter.com/search?q=Mandetta",
                "promoted_content": null,
                "query": "Mandetta",
                "tweet_volume": 423118
            },
            {
                "name": "Ministro da Sa\u00fade",
                "url": "http://twitter.com/search?q=%22Ministro+da+Sa%C3%BAde%22",
                "promoted_content": null,
                "query": "%22Ministro+da+Sa%C3%BAde%22",
                "tweet_volume": 178755
            },
            {
                "name": "Bozo",
                "url": "http://twitter.com/search?q=Bozo",
                "promoted_content": null,
                "query": "Bozo",
                "tweet_volume": 32623
            },
            {
                "name": "Globo",
                "url": "http://twitter.com/search?q=Globo",
                "promoted_content": null,
                "query": "Globo",
                "tweet_volume": 190207
            },
            {
                "name": "#auxilioemergencialaprovado",
                "url": "http://twitter.com/search?q=%23auxilioemergencialaprovado",
                "promoted_content": null,
                "query": "%23auxilioemergencialaprovado",
                "tweet_volume": 18481
            },
            {
                "name": "#ImpeachmentJ\u00e1",
                "url": "http://twitter.com/search?q=%23ImpeachmentJ%C3%A1",
                "promoted_content": null,
                "query": "%23ImpeachmentJ%C3%A1",
                "tweet_volume": null
            },
            {
                "name": "#STFVergonhaNacional",
                "url": "http://twitter.com/search?q=%23STFVergonhaNacional",
                "promoted_content": null,
                "query": "%23STFVergonhaNacional",
                "tweet_volume": 43422
            },
            {
                "name": "#ImReadyTONIGHT",
                "url": "http://twitter.com/search?q=%23ImReadyTONIGHT",
                "promoted_content": null,
                "query": "%23ImReadyTONIGHT",
                "tweet_volume": null
            },
            {
                "name": "Help Brazil",
                "url": "http://twitter.com/search?q=%22Help+Brazil%22",
                "promoted_content": null,
                "query": "%22Help+Brazil%22",
                "tweet_volume": null
            },
            {
                "name": "Haddad",
                "url": "http://twitter.com/search?q=Haddad",
                "promoted_content": null,
                "query": "Haddad",
                "tweet_volume": null
            },
            {
                "name": "Carmem L\u00facia",
                "url": "http://twitter.com/search?q=%22Carmem+L%C3%BAcia%22",
                "promoted_content": null,
                "query": "%22Carmem+L%C3%BAcia%22",
                "tweet_volume": null
            },
            {
                "name": "Fl\u00e1vio Dino",
                "url": "http://twitter.com/search?q=%22Fl%C3%A1vio+Dino%22",
                "promoted_content": null,
                "query": "%22Fl%C3%A1vio+Dino%22",
                "tweet_volume": 23806
            },
            {
                "name": "TOMA TEN\u00caNCIA",
                "url": "http://twitter.com/search?q=%22TOMA+TEN%C3%8ANCIA%22",
                "promoted_content": null,
                "query": "%22TOMA+TEN%C3%8ANCIA%22",
                "tweet_volume": null
            },
            {
                "name": "Mais M\u00e9dicos",
                "url": "http://twitter.com/search?q=%22Mais+M%C3%A9dicos%22",
                "promoted_content": null,
                "query": "%22Mais+M%C3%A9dicos%22",
                "tweet_volume": null
            },
            {
                "name": "Demitiu",
                "url": "http://twitter.com/search?q=Demitiu",
                "promoted_content": null,
                "query": "Demitiu",
                "tweet_volume": 49751
            },
            {
                "name": "BUZZFEED APOIA CYBERBULLYING",
                "url": "http://twitter.com/search?q=%22BUZZFEED+APOIA+CYBERBULLYING%22",
                "promoted_content": null,
                "query": "%22BUZZFEED+APOIA+CYBERBULLYING%22",
                "tweet_volume": 25281
            },
            {
                "name": "Biroliro",
                "url": "http://twitter.com/search?q=Biroliro",
                "promoted_content": null,
                "query": "Biroliro",
                "tweet_volume": null
            },
            {
                "name": "Pimp\u00e3o",
                "url": "http://twitter.com/search?q=Pimp%C3%A3o",
                "promoted_content": null,
                "query": "Pimp%C3%A3o",
                "tweet_volume": null
            },
            {
                "name": "Osmar",
                "url": "http://twitter.com/search?q=Osmar",
                "promoted_content": null,
                "query": "Osmar",
                "tweet_volume": 17164
            },
            {
                "name": "Fabiano",
                "url": "http://twitter.com/search?q=Fabiano",
                "promoted_content": null,
                "query": "Fabiano",
                "tweet_volume": 11478
            },
            {
                "name": "Nosso SUS",
                "url": "http://twitter.com/search?q=%22Nosso+SUS%22",
                "promoted_content": null,
                "query": "%22Nosso+SUS%22",
                "tweet_volume": 24311
            },
            {
                "name": "Will Smith",
                "url": "http://twitter.com/search?q=%22Will+Smith%22",
                "promoted_content": null,
                "query": "%22Will+Smith%22",
                "tweet_volume": 24814
            },
            {
                "name": "Oncologista",
                "url": "http://twitter.com/search?q=Oncologista",
                "promoted_content": null,
                "query": "Oncologista",
                "tweet_volume": 19211
            },
            {
                "name": "BALADA DO BEBE MVAD",
                "url": "http://twitter.com/search?q=%22BALADA+DO+BEBE+MVAD%22",
                "promoted_content": null,
                "query": "%22BALADA+DO+BEBE+MVAD%22",
                "tweet_volume": null
            },
            {
                "name": "#MTVHitsOiSumido",
                "url": "http://twitter.com/search?q=%23MTVHitsOiSumido",
                "promoted_content": null,
                "query": "%23MTVHitsOiSumido",
                "tweet_volume": null
            }
        ],
        "as_of": "2020-04-16T21:23:07Z",
        "created_at": "2020-04-16T21:17:17Z",
        "locations": [
            {
                "name": "Brazil",
                "woeid": 23424768
            }
        ]
    }
]